scrapy_pipelines/__init__.py
scrapy_pipelines/_version.py
scrapy_pipelines/item.py
scrapy_pipelines/signals.py
scrapy_pipelines/pipelines/__init__.py
scrapy_pipelines/pipelines/mongo.py
scrapy_pipelines/settings/__init__.py
scrapy_pipelines/settings/default_settings.py
Scrapy_Pipelines-0.2.dist-info/LICENSE
Scrapy_Pipelines-0.2.dist-info/METADATA
Scrapy_Pipelines-0.2.dist-info/WHEEL
Scrapy_Pipelines-0.2.dist-info/top_level.txt
Scrapy_Pipelines-0.2.dist-info/RECORD
