Metadata-Version: 2.1
Name: Scrapy-Pipelines
Version: 0.2
Summary: A collection of scrapy item pipelines
Home-page: https://github.com/scrapedia/scrapy-pipelines
Author: Scrapedia
Author-email: Scrapedia@outlook.com
Maintainer: Scrapedia
Maintainer-email: Scrapedia@outlook.com
License: GPLv3
Platform: UNKNOWN
Classifier: Framework :: Scrapy
Classifier: Development Status :: 2 - Pre-Alpha
Classifier: Environment :: Plugins
Classifier: Intended Audience :: Developers
Classifier: Operating System :: OS Independent
Classifier: Programming Language :: Python
Classifier: Programming Language :: Python :: 3
Classifier: Programming Language :: Python :: 3.6
Classifier: Programming Language :: Python :: 3.7
Classifier: Topic :: Internet :: WWW/HTTP
Classifier: Topic :: Software Development :: Libraries :: Python Modules
Requires-Dist: scrapy
Requires-Dist: txmongo
